[{"model": "admin.logentry", "pk": 1, "fields": {"action_time": "2022-07-16T00:29:08.204Z", "user": 1, "content_type": 7, "object_id": "1", "object_repr": "Lucky's Pub", "action_flag": 1, "change_message": "[{\"added\": {}}]"}}, {"model": "admin.logentry", "pk": 2, "fields": {"action_time": "2022-07-16T00:37:11.371Z", "user": 1, "content_type": 4, "object_id": "2", "object_repr": "amber2", "action_flag": 1, "change_message": "[{\"added\": {}}]"}}, {"model": "admin.logentry", "pk": 3, "fields": {"action_time": "2022-07-17T15:23:48.659Z", "user": 1, "content_type": 7, "object_id": "8", "object_repr": "Lucky's Pub", "action_flag": 2, "change_message": "[{\"changed\": {\"fields\": [\"Title\"]}}]"}}, {"model": "admin.logentry", "pk": 4, "fields": {"action_time": "2022-07-17T15:29:34.040Z", "user": 1, "content_type": 7, "object_id": "9", "object_repr": "pockets billiards", "action_flag": 3, "change_message": ""}}, {"model": "admin.logentry", "pk": 5, "fields": {"action_time": "2022-07-17T15:29:34.046Z", "user": 1, "content_type": 7, "object_id": "8", "object_repr": "Lucky's Pub", "action_flag": 3, "change_message": ""}}, {"model": "admin.logentry", "pk": 6, "fields": {"action_time": "2022-07-17T15:29:34.049Z", "user": 1, "content_type": 7, "object_id": "7", "object_repr": "a", "action_flag": 3, "change_message": ""}}, {"model": "admin.logentry", "pk": 7, "fields": {"action_time": "2022-07-17T15:29:34.054Z", "user": 1, "content_type": 7, "object_id": "6", "object_repr": "a", "action_flag": 3, "change_message": ""}}, {"model": "admin.logentry", "pk": 8, "fields": {"action_time": "2022-07-17T15:29:34.059Z", "user": 1, "content_type": 7, "object_id": "5", "object_repr": "a", "action_flag": 3, "change_message": ""}}, {"model": "admin.logentry", "pk": 9, "fields": {"action_time": "2022-07-17T15:29:34.062Z", "user": 1, "content_type": 7, "object_id": "4", "object_repr": "a", "action_flag": 3, "change_message": ""}}, {"model": "admin.logentry", "pk": 10, "fields": {"action_time": "2022-07-17T15:29:34.065Z", "user": 1, "content_type": 7, "object_id": "3", "object_repr": "a", "action_flag": 3, "change_message": ""}}, {"model": "admin.logentry", "pk": 11, "fields": {"action_time": "2022-07-17T15:29:34.068Z", "user": 1, "content_type": 7, "object_id": "2", "object_repr": "a", "action_flag": 3, "change_message": ""}}, {"model": "admin.logentry", "pk": 12, "fields": {"action_time": "2022-07-17T15:29:34.071Z", "user": 1, "content_type": 7, "object_id": "1", "object_repr": "Lucky's Pub", "action_flag": 3, "change_message": ""}}, {"model": "admin.logentry", "pk": 13, "fields": {"action_time": "2022-07-17T15:30:12.513Z", "user": 1, "content_type": 7, "object_id": "10", "object_repr": "pockets billiards", "action_flag": 1, "change_message": "[{\"added\": {}}]"}}, {"model": "admin.logentry", "pk": 14, "fields": {"action_time": "2022-07-22T16:58:29.744Z", "user": 1, "content_type": 8, "object_id": "4defcf1f-1509-48f7-ba1f-6defeb1cb465", "object_repr": "Aloysius Yapp", "action_flag": 1, "change_message": "[{\"added\": {}}]"}}, {"model": "admin.logentry", "pk": 15, "fields": {"action_time": "2022-07-22T17:01:15.856Z", "user": 1, "content_type": 8, "object_id": "39903f60-0747-4f2c-88f7-80a43c88739f", "object_repr": "Joshua Filler", "action_flag": 1, "change_message": "[{\"added\": {}}]"}}, {"model": "admin.logentry", "pk": 16, "fields": {"action_time": "2022-07-22T17:05:25.055Z", "user": 1, "content_type": 8, "object_id": "4f19b166-d798-4b4c-9ff4-f6fed518d1ca", "object_repr": "Fedor Gorst", "action_flag": 1, "change_message": "[{\"added\": {}}]"}}, {"model": "admin.logentry", "pk": 17, "fields": {"action_time": "2022-07-23T00:57:19.019Z", "user": 1, "content_type": 9, "object_id": "b0ece9d2-314a-49b4-8c09-a84cd6add250", "object_repr": "Kelly Fisher Finds Trophy in Trash Can", "action_flag": 1, "change_message": "[{\"added\": {}}]"}}, {"model": "admin.logentry", "pk": 18, "fields": {"action_time": "2022-07-23T01:00:51.280Z", "user": 1, "content_type": 9, "object_id": "b0ece9d2-314a-49b4-8c09-a84cd6add250", "object_repr": "Kelly Fisher Finds Trophy in Trash Can", "action_flag": 2, "change_message": "[{\"changed\": {\"fields\": [\"Article\"]}}]"}}, {"model": "admin.logentry", "pk": 19, "fields": {"action_time": "2022-07-23T01:26:06.222Z", "user": 1, "content_type": 9, "object_id": "47aeb031-539d-4f1a-9fe4-566896b4cae3", "object_repr": "https://www.azbilliards.com/wp-content/uploads/cache/remote/assets-azbilliards-com/2490693453.jpg", "action_flag": 1, "change_message": "[{\"added\": {}}]"}}, {"model": "admin.logentry", "pk": 20, "fields": {"action_time": "2022-07-23T01:26:45.003Z", "user": 1, "content_type": 9, "object_id": "47aeb031-539d-4f1a-9fe4-566896b4cae3", "object_repr": "Jason Shaw Dominates the Mosconi Cup", "action_flag": 2, "change_message": "[{\"changed\": {\"fields\": [\"Title\"]}}]"}}, {"model": "admin.logentry", "pk": 21, "fields": {"action_time": "2022-07-23T01:30:38.192Z", "user": 1, "content_type": 9, "object_id": "acc237f1-aee2-4eeb-aa09-6ac72dcd4569", "object_repr": "Francisco Sanchez-Ruiz", "action_flag": 1, "change_message": "[{\"added\": {}}]"}}, {"model": "admin.logentry", "pk": 22, "fields": {"action_time": "2022-07-23T01:37:47.713Z", "user": 1, "content_type": 9, "object_id": "47aeb031-539d-4f1a-9fe4-566896b4cae3", "object_repr": "Jason Shaw Dominates the Mosconi Cup", "action_flag": 2, "change_message": "[{\"changed\": {\"fields\": [\"Image\"]}}]"}}, {"model": "admin.logentry", "pk": 23, "fields": {"action_time": "2022-07-23T01:50:11.054Z", "user": 1, "content_type": 9, "object_id": "b0ece9d2-314a-49b4-8c09-a84cd6add250", "object_repr": "Kelly Fisher Finds Her Stolen Trophy in Trash Can", "action_flag": 2, "change_message": "[{\"changed\": {\"fields\": [\"Title\"]}}]"}}, {"model": "admin.logentry", "pk": 24, "fields": {"action_time": "2022-07-23T02:34:25.295Z", "user": 1, "content_type": 7, "object_id": "a95de46c-2fc7-48d4-9f97-474205b6778a", "object_repr": "veteran's billiards", "action_flag": 1, "change_message": "[{\"added\": {}}]"}}, {"model": "admin.logentry", "pk": 25, "fields": {"action_time": "2022-07-23T04:12:28.821Z", "user": 1, "content_type": 9, "object_id": "acc237f1-aee2-4eeb-aa09-6ac72dcd4569", "object_repr": "Francisco Sanchez-Ruiz Wins it All", "action_flag": 2, "change_message": "[{\"changed\": {\"fields\": [\"Title\", \"Description\"]}}]"}}, {"model": "auth.permission", "pk": 1, "fields": {"name": "Can add log entry", "content_type": 1, "codename": "add_logentry"}}, {"model": "auth.permission", "pk": 2, "fields": {"name": "Can change log entry", "content_type": 1, "codename": "change_logentry"}}, {"model": "auth.permission", "pk": 3, "fields": {"name": "Can delete log entry", "content_type": 1, "codename": "delete_logentry"}}, {"model": "auth.permission", "pk": 4, "fields": {"name": "Can view log entry", "content_type": 1, "codename": "view_logentry"}}, {"model": "auth.permission", "pk": 5, "fields": {"name": "Can add permission", "content_type": 2, "codename": "add_permission"}}, {"model": "auth.permission", "pk": 6, "fields": {"name": "Can change permission", "content_type": 2, "codename": "change_permission"}}, {"model": "auth.permission", "pk": 7, "fields": {"name": "Can delete permission", "content_type": 2, "codename": "delete_permission"}}, {"model": "auth.permission", "pk": 8, "fields": {"name": "Can view permission", "content_type": 2, "codename": "view_permission"}}, {"model": "auth.permission", "pk": 9, "fields": {"name": "Can add group", "content_type": 3, "codename": "add_group"}}, {"model": "auth.permission", "pk": 10, "fields": {"name": "Can change group", "content_type": 3, "codename": "change_group"}}, {"model": "auth.permission", "pk": 11, "fields": {"name": "Can delete group", "content_type": 3, "codename": "delete_group"}}, {"model": "auth.permission", "pk": 12, "fields": {"name": "Can view group", "content_type": 3, "codename": "view_group"}}, {"model": "auth.permission", "pk": 13, "fields": {"name": "Can add user", "content_type": 4, "codename": "add_user"}}, {"model": "auth.permission", "pk": 14, "fields": {"name": "Can change user", "content_type": 4, "codename": "change_user"}}, {"model": "auth.permission", "pk": 15, "fields": {"name": "Can delete user", "content_type": 4, "codename": "delete_user"}}, {"model": "auth.permission", "pk": 16, "fields": {"name": "Can view user", "content_type": 4, "codename": "view_user"}}, {"model": "auth.permission", "pk": 17, "fields": {"name": "Can add content type", "content_type": 5, "codename": "add_contenttype"}}, {"model": "auth.permission", "pk": 18, "fields": {"name": "Can change content type", "content_type": 5, "codename": "change_contenttype"}}, {"model": "auth.permission", "pk": 19, "fields": {"name": "Can delete content type", "content_type": 5, "codename": "delete_contenttype"}}, {"model": "auth.permission", "pk": 20, "fields": {"name": "Can view content type", "content_type": 5, "codename": "view_contenttype"}}, {"model": "auth.permission", "pk": 21, "fields": {"name": "Can add session", "content_type": 6, "codename": "add_session"}}, {"model": "auth.permission", "pk": 22, "fields": {"name": "Can change session", "content_type": 6, "codename": "change_session"}}, {"model": "auth.permission", "pk": 23, "fields": {"name": "Can delete session", "content_type": 6, "codename": "delete_session"}}, {"model": "auth.permission", "pk": 24, "fields": {"name": "Can view session", "content_type": 6, "codename": "view_session"}}, {"model": "auth.permission", "pk": 25, "fields": {"name": "Can add listing", "content_type": 7, "codename": "add_listing"}}, {"model": "auth.permission", "pk": 26, "fields": {"name": "Can change listing", "content_type": 7, "codename": "change_listing"}}, {"model": "auth.permission", "pk": 27, "fields": {"name": "Can delete listing", "content_type": 7, "codename": "delete_listing"}}, {"model": "auth.permission", "pk": 28, "fields": {"name": "Can view listing", "content_type": 7, "codename": "view_listing"}}, {"model": "auth.permission", "pk": 29, "fields": {"name": "Can add featured player", "content_type": 8, "codename": "add_featuredplayer"}}, {"model": "auth.permission", "pk": 30, "fields": {"name": "Can change featured player", "content_type": 8, "codename": "change_featuredplayer"}}, {"model": "auth.permission", "pk": 31, "fields": {"name": "Can delete featured player", "content_type": 8, "codename": "delete_featuredplayer"}}, {"model": "auth.permission", "pk": 32, "fields": {"name": "Can view featured player", "content_type": 8, "codename": "view_featuredplayer"}}, {"model": "auth.permission", "pk": 33, "fields": {"name": "Can add news", "content_type": 9, "codename": "add_news"}}, {"model": "auth.permission", "pk": 34, "fields": {"name": "Can change news", "content_type": 9, "codename": "change_news"}}, {"model": "auth.permission", "pk": 35, "fields": {"name": "Can delete news", "content_type": 9, "codename": "delete_news"}}, {"model": "auth.permission", "pk": 36, "fields": {"name": "Can view news", "content_type": 9, "codename": "view_news"}}, {"model": "auth.user", "pk": 1, "fields": {"password": "pbkdf2_sha256$320000$kfZNZ3gN1diA3rp9GdajWU$qVaj+d3V2HBNDkd32+10WJlp/G0PEM98b5ko8IMyFrs=", "last_login": "2022-08-11T17:35:48.356Z", "is_superuser": true, "username": "amber", "first_name": "", "last_name": "", "email": "amberbjankowski@gmail.com", "is_staff": true, "is_active": true, "date_joined": "2022-07-16T00:25:20.781Z", "groups": [], "user_permissions": []}}, {"model": "auth.user", "pk": 2, "fields": {"password": "pbkdf2_sha256$320000$ldepeRABwaXLowfrwOl6Rt$BZcGMx+WKj4qERuWKHu5cr/5bu69aVzddGBd6J2ewLk=", "last_login": null, "is_superuser": false, "username": "amber2", "first_name": "", "last_name": "", "email": "", "is_staff": false, "is_active": true, "date_joined": "2022-07-16T00:37:10.000Z", "groups": [], "user_permissions": []}}, {"model": "auth.user", "pk": 3, "fields": {"password": "pbkdf2_sha256$320000$0Yivb9FqFYLFq4PWO9tHEB$1SfczTKkfDYcHaWZbb0it8/A8wrICfKbVJxWdYAtGPo=", "last_login": null, "is_superuser": true, "username": "amjann", "first_name": "", "last_name": "", "email": "amber@gmail.com", "is_staff": true, "is_active": true, "date_joined": "2022-07-22T22:57:19.168Z", "groups": [], "user_permissions": []}}, {"model": "auth.user", "pk": 4, "fields": {"password": "pbkdf2_sha256$320000$MpIvXQZQr2HBPeEWe3SXvN$/tLxz/Qs/vZy8mXFF28KJM1OvR/ZymmPfHBGD9eCaCk=", "last_login": null, "is_superuser": true, "username": "admin", "first_name": "", "last_name": "", "email": "amberbjankowski@gmail.com", "is_staff": true, "is_active": true, "date_joined": "2022-07-29T19:47:42.182Z", "groups": [], "user_permissions": []}}, {"model": "contenttypes.contenttype", "pk": 1, "fields": {"app_label": "admin", "model": "logentry"}}, {"model": "contenttypes.contenttype", "pk": 2, "fields": {"app_label": "auth", "model": "permission"}}, {"model": "contenttypes.contenttype", "pk": 3, "fields": {"app_label": "auth", "model": "group"}}, {"model": "contenttypes.contenttype", "pk": 4, "fields": {"app_label": "auth", "model": "user"}}, {"model": "contenttypes.contenttype", "pk": 5, "fields": {"app_label": "contenttypes", "model": "contenttype"}}, {"model": "contenttypes.contenttype", "pk": 6, "fields": {"app_label": "sessions", "model": "session"}}, {"model": "contenttypes.contenttype", "pk": 7, "fields": {"app_label": "tournament", "model": "listing"}}, {"model": "contenttypes.contenttype", "pk": 8, "fields": {"app_label": "tournament", "model": "featuredplayer"}}, {"model": "contenttypes.contenttype", "pk": 9, "fields": {"app_label": "tournament", "model": "news"}}, {"model": "sessions.session", "pk": "av1ysqjholvdmxfad9c1aurr51kz4000", "fields": {"session_data": ".eJxVjEEOwiAQRe_C2hAGKgMu3fcMZGCoVA0kpV0Z765NutDtf-_9lwi0rSVsPS9hZnERIE6_W6T0yHUHfKd6azK1ui5zlLsiD9rl2Dg_r4f7d1Col2_tlMo2q8jROUzKeuUACQ0M4BEpaRwm48CDjoxg_OQtnJkHCwl0diDeH7fHNok:1oCVcr:9jN6srjD0FjBMeE69275cRtreCvHw9qtjCPawGcGA7U", "expire_date": "2022-07-30T00:25:41.378Z"}}, {"model": "sessions.session", "pk": "dq4nuxb1d0pwr4it7v73en1nxca1p79j", "fields": {"session_data": ".eJxVjEEOwiAQRe_C2hAGKgMu3fcMZGCoVA0kpV0Z765NutDtf-_9lwi0rSVsPS9hZnERIE6_W6T0yHUHfKd6azK1ui5zlLsiD9rl2Dg_r4f7d1Col2_tlMo2q8jROUzKeuUACQ0M4BEpaRwm48CDjoxg_OQtnJkHCwl0diDeH7fHNok:1oMC60:5U7oyxvHfutEUtcdXNTF55zKtuDf4eBe3GrWzYLvw_o", "expire_date": "2022-08-25T17:35:48.400Z"}}, {"model": "sessions.session", "pk": "zuex33a3t59d1l14zcofkdvu9zms3fiv", "fields": {"session_data": ".eJxVjEEOwiAQRe_C2hAGKgMu3fcMZGCoVA0kpV0Z765NutDtf-_9lwi0rSVsPS9hZnERIE6_W6T0yHUHfKd6azK1ui5zlLsiD9rl2Dg_r4f7d1Col2_tlMo2q8jROUzKeuUACQ0M4BEpaRwm48CDjoxg_OQtnJkHCwl0diDeH7fHNok:1oF1ai:j6Hm8jcwFpov2uouGQz21O_M9E6K0cTwKHNJm77ui-Q", "expire_date": "2022-08-05T22:57:52.868Z"}}, {"model": "tournament.listing", "pk": "a3d58e4a-2f35-4a58-bf63-5cea8f3927e5", "fields": {"title": "9-ball weekly tournament", "director": "Amber Jankowski", "phone_number": "9412753331", "email": "amberbjankowski@gmail.com", "venue": "pockets billiards", "address": "4524 South Cranberry Boulevard", "city": "North Port", "state": "FL", "zipcode": 34286, "date": "2022-08-13", "sign_up_time": "1 pm", "start_time": "2 pm", "description": "Race to three on winners and race to two on Losers,9ft tables, no handicap"}}, {"model": "tournament.listing", "pk": "a95de46c-2fc7-48d4-9f97-474205b6778a", "fields": {"title": "8 -ball Pool Tournament", "director": "Doug", "phone_number": "9412753331", "email": "amberbjankowski@gmail.com", "venue": "veteran's billiards", "address": "4524 South Cranberry Boulevard", "city": "North Port", "state": "FL", "zipcode": 34286, "date": "2022-07-28", "sign_up_time": "5:00 pm", "start_time": "6:00pm", "description": "Race to 5, winner breaks, BCA rules."}}, {"model": "tournament.featuredplayer", "pk": "39903f60-0747-4f2c-88f7-80a43c88739f", "fields": {"name": "Joshua Filler", "birth_date": "1997-10-02", "country": "Germany", "fargo": 836, "current_year_earnings": "$122,413.00", "image": "https://assets.azbilliards.com/wp-content/uploads/2020/08/19011623/DSC_5628.jpg", "description": "Lorem ipsum, dolor sit amet consectetur adipisicing elit. Nisi exercitationem dolore molestias ratione libero? Repellat, distinctio vitae. Fuga ex voluptatibus, iste id provident rerum libero iusto exercitationem soluta autem quaerat!Nisi exercitationem dolore molestias ratione libero? Repellat, distinctio vitae. Fuga ex voluptatibus, iste id provident rerum libero iusto exercitationem soluta autem quaerat!\r\n Lorem ipsum, dolor sit amet consectetur adipisicing elit. Nisi exercitationem dolore molestias ratione libero? Repellat, distinctio vitae. Fuga ex voluptatibus, iste id provident rerum libero iusto exercitationem soluta autem quaerat!Nisi exercitationem dolore molestias ratione libero? Repellat, distinctio vitae. Fuga ex voluptatibus, iste id provident rerum libero iusto exercitationem soluta autem quaerat!\r\n   dolor sit amet consectetur adipisicing elit. Nisi exercitationem dolore molestias ratione libero? Repellat, distinctio vitae. Fuga ex voluptatibus, iste id provident rerum libero iusto exercitationem soluta autem quaerat!Nisi exercitationem dolore molestias ratione libero? Repellat, distinctio vitae. Fuga ex voluptatibus, iste id provident rerum libero iusto exercitationem soluta autem quaerat!"}}, {"model": "tournament.featuredplayer", "pk": "4defcf1f-1509-48f7-ba1f-6defeb1cb465", "fields": {"name": "Aloysius Yapp", "birth_date": "1992-05-02", "country": "Singapore", "fargo": 813, "current_year_earnings": "$51,575.00", "image": "https://assets.azbilliards.com/wp-content/uploads/2021/09/22195929/e0ce1800-194a-11ec-adbf-b6042bebd7bb.jpg", "description": "Lorem ipsum, dolor sit amet consectetur adipisicing elit. Nisi exercitationem dolore molestias ratione libero? Repellat, distinctio vitae. Fuga ex voluptatibus, iste id provident rerum libero iusto exercitationem soluta autem quaerat!Nisi exercitationem dolore molestias ratione libero? Repellat, distinctio vitae. Fuga ex voluptatibus, iste id provident rerum libero iusto exercitationem soluta autem quaerat!\r\n Lorem ipsum, dolor sit amet consectetur adipisicing elit. Nisi exercitationem dolore molestias ratione libero? Repellat, distinctio vitae. Fuga ex voluptatibus, iste id provident rerum libero iusto exercitationem soluta autem quaerat!Nisi exercitationem dolore molestias ratione libero? Repellat, distinctio vitae. Fuga ex voluptatibus, iste id provident rerum libero iusto exercitationem soluta autem quaerat!\r\n   dolor sit amet consectetur adipisicing elit. Nisi exercitationem dolore molestias ratione libero? Repellat, distinctio vitae. Fuga ex voluptatibus, iste id provident rerum libero iusto exercitationem soluta autem quaerat!Nisi exercitationem dolore molestias ratione libero? Repellat, distinctio vitae. Fuga ex voluptatibus, iste id provident rerum libero iusto exercitationem soluta autem quaerat!"}}, {"model": "tournament.featuredplayer", "pk": "4f19b166-d798-4b4c-9ff4-f6fed518d1ca", "fields": {"name": "Fedor Gorst", "birth_date": "2000-05-31", "country": "Russia", "fargo": 824, "current_year_earnings": "$158,992.00", "image": "https://assets.azbilliards.com/wp-content/uploads/2021/06/08174258/Fedor-Gorst-1.jpg", "description": "Lorem ipsum, dolor sit amet consectetur adipisicing elit. Nisi exercitationem dolore molestias ratione libero? Repellat, distinctio vitae. Fuga ex voluptatibus, iste id provident rerum libero iusto exercitationem soluta autem quaerat!Nisi exercitationem dolore molestias ratione libero? Repellat, distinctio vitae. Fuga ex voluptatibus, iste id provident rerum libero iusto exercitationem soluta autem quaerat!\r\n Lorem ipsum, dolor sit amet consectetur adipisicing elit. Nisi exercitationem dolore molestias ratione libero? Repellat, distinctio vitae. Fuga ex voluptatibus, iste id provident rerum libero iusto exercitationem soluta autem quaerat!Nisi exercitationem dolore molestias ratione libero? Repellat, distinctio vitae. Fuga ex voluptatibus, iste id provident rerum libero iusto exercitationem soluta autem quaerat!\r\n   dolor sit amet consectetur adipisicing elit. Nisi exercitationem dolore molestias ratione libero? Repellat, distinctio vitae. Fuga ex voluptatibus, iste id provident rerum libero iusto exercitationem soluta autem quaerat!Nisi exercitationem dolore molestias ratione libero? Repellat, distinctio vitae. Fuga ex voluptatibus, iste id provident rerum libero iusto exercitationem soluta autem quaerat!"}}, {"model": "tournament.news", "pk": "47aeb031-539d-4f1a-9fe4-566896b4cae3", "fields": {"title": "Jason Shaw Dominates the Mosconi Cup", "author": "Jon Doe", "image": "https://assets.azbilliards.com/wp-content/uploads/2021/08/31205308/DSC_7867-5150.jpg", "date": "2022-07-20", "article": "Lorem ipsum, dolor sit amet consectetur adipisicing elit. Nisi exercitationem dolore molestias ratione libero? Repellat, distinctio vitae. Fuga ex voluptatibus, iste id provident rerum libero iusto exercitationem soluta autem quaerat!Nisi exercitationem dolore molestias ratione libero? Repellat, distinctio vitae. Fuga ex voluptatibus, iste id provident rerum libero iusto exercitationem soluta autem quaerat!\r\n Lorem ipsum, dolor sit amet consectetur adipisicing elit. Nisi exercitationem dolore molestias ratione libero? Repellat, distinctio vitae. Fuga ex voluptatibus, iste id provident rerum libero iusto exercitationem soluta autem quaerat!Nisi exercitationem dolore molestias ratione libero? Repellat, distinctio vitae. Fuga ex voluptatibus, iste id provident rerum libero iusto exercitationem soluta autem quaerat!\r\n   dolor sit amet consectetur adipisicing elit. Nisi exercitationem dolore molestias ratione libero? Repellat, distinctio vitae. Fuga ex voluptatibus, iste id provident rerum libero iusto exercitationem soluta autem quaerat!Nisi exercitationem dolore molestias ratione libero? Repellat, distinctio vitae. Fuga ex voluptatibus, iste id provident rerum libero iusto exercitationem soluta autem quaerat!", "description": "Jason Shaw is victorious after playing the final match in the Mosconi cup,. He couldn't put his arms down from the work he put into playing. Medical officials looked into and said ..."}}, {"model": "tournament.news", "pk": "acc237f1-aee2-4eeb-aa09-6ac72dcd4569", "fields": {"title": "Francisco Sanchez-Ruiz Wins it All", "author": "Jane Doe", "image": "https://assets.azbilliards.com/wp-content/uploads/2021/08/31205304/DSC_7859-5049.jpg", "date": "2022-07-19", "article": "Lorem ipsum, dolor sit amet consectetur adipisicing elit. Nisi exercitationem dolore molestias ratione libero? Repellat, distinctio vitae. Fuga ex voluptatibus, iste id provident rerum libero iusto exercitationem soluta autem quaerat!Nisi exercitationem dolore molestias ratione libero? Repellat, distinctio vitae. Fuga ex voluptatibus, iste id provident rerum libero iusto exercitationem soluta autem quaerat!\r\n Lorem ipsum, dolor sit amet consectetur adipisicing elit. Nisi exercitationem dolore molestias ratione libero? Repellat, distinctio vitae. Fuga ex voluptatibus, iste id provident rerum libero iusto exercitationem soluta autem quaerat!Nisi exercitationem dolore molestias ratione libero? Repellat, distinctio vitae. Fuga ex voluptatibus, iste id provident rerum libero iusto exercitationem soluta autem quaerat!\r\n   dolor sit amet consectetur adipisicing elit. Nisi exercitationem dolore molestias ratione libero? Repellat, distinctio vitae. Fuga ex voluptatibus, iste id provident rerum libero iusto exercitationem soluta autem quaerat!Nisi exercitationem dolore molestias ratione libero? Repellat, distinctio vitae. Fuga ex voluptatibus, iste id provident rerum libero iusto exercitationem soluta autem quaerat!", "description": "Francisco Sanchez-Ruiz makes waves in the U.S. Open beating his final opponent Cory Deuel one handed in the final match. Beating him with the score being 13 to..."}}, {"model": "tournament.news", "pk": "b0ece9d2-314a-49b4-8c09-a84cd6add250", "fields": {"title": "Kelly Fisher Finds Her Stolen Trophy in Trash Can", "author": "Jane Doe", "image": "https://assets.azbilliards.com/wp-content/uploads/2020/07/20000824/Kelly_FIsher_july13.jpg", "date": "2022-07-23", "article": "Lorem ipsum, dolor sit amet consectetur adipisicing elit. Nisi exercitationem dolore molestias ratione libero? Repellat, distinctio vitae. Fuga ex voluptatibus, iste id provident rerum libero iusto exercitationem soluta autem quaerat!Nisi exercitationem dolore molestias ratione libero? Repellat, distinctio vitae. Fuga ex voluptatibus, iste id provident rerum libero iusto exercitationem soluta autem quaerat!  \r\n      Lorem ipsum, dolor sit amet consectetur adipisicing elit. Nisi exercitationem dolore molestias ratione libero? Repellat, distinctio vitae. Fuga ex voluptatibus, iste id provident rerum libero iusto exercitationem soluta autem quaerat!Nisi exercitationem dolore molestias ratione libero? Repellat, distinctio vitae. Fuga ex voluptatibus, iste id provident rerum libero iusto exercitationem soluta autem quaerat!    \r\n      dolor sit amet consectetur adipisicing elit. Nisi exercitationem dolore molestias ratione libero? Repellat, distinctio vitae. Fuga ex voluptatibus, iste id provident rerum libero iusto exercitationem soluta autem quaerat!Nisi exercitationem dolore molestias ratione libero? Repellat, distinctio vitae. Fuga ex voluptatibus, iste id provident rerum libero iusto exercitationem soluta autem quaerat!", "description": "Kelly Fisher serendipitously finds trophy that she won in a garbage can. After a long two days of competitive playing, her trophy went missing..."}}]